furypie/__init__.py
furypie/helper.py
furypie-0.2.dist-info/LICENSE
furypie-0.2.dist-info/METADATA
furypie-0.2.dist-info/WHEEL
furypie-0.2.dist-info/entry_points.txt
furypie-0.2.dist-info/top_level.txt
furypie-0.2.dist-info/RECORD
