Metadata-Version: 2.1
Name: furypie
Version: 0.2
Summary: Install private python packages from gemfury
Author-email: Soumyo Deep Gupta <deep.main.ac@gmail.com>
Maintainer-email: Soumyo Deep Gupta <deep.main.ac@gmail.com>
License: MIT License
Project-URL: GitHub, https://github.com/d33pster/gemfury-installer
Keywords: d33pster,gemfury,fury,furypie,pyfury
Classifier: Programming Language :: Python :: 3.12
Classifier: Operating System :: OS Independent
Classifier: License :: OSI Approved :: MIT License
Requires-Python: >=3.12
License-File: LICENSE
Requires-Dist: ende
Requires-Dist: argpi
